<?xml version="1.0" encoding="utf-8"?>
<root>
	<basic>
		<rarity>5</rarity>
		<id>77</id>
		<name_sc>尼古拉·特斯拉</name_sc>
		<name_jp>ニコラ･テスラ</name_jp>
		<name_en>Nikola Tesla</name_en>
		<class>Archer</class>
		<alignments>混沌</alignments>
		<alignments>善</alignments>
		<gender>男性</gender>
		<attribute>星</attribute>
		<atk_base>1820</atk_base>
		<hp_base>2027</hp_base>
		<atk_4>11781</atk_4>
		<hp_4>13825</hp_4>
		<atk_90>11781</atk_90>
		<hp_90>13825</hp_90>
		<atk_100>12896</atk_100>
		<hp_100>15146</hp_100>
		<atk_max>14896</atk_max>
		<hp_max>17146</hp_max>
		<card>QAABB</card>
		<characteristic>人型</characteristic>
		<characteristic>不被EA特攻</characteristic>
		<characteristic>所爱之人</characteristic>
		<nickname>特总</nickname>
	</basic>
	<nobel>
		<revealable>False</revealable>
		<upgradable>True</upgradable>
		<card>B</card>
		<level>EX</level>
		<name_sc>人类神话·雷电降临</name_sc>
		<name_jp>人類神話·雷電降臨</name_jp>
		<name_en>System Keraunos</name_en>
	</nobel>
	<ascension_consume>
		<consume_rarity>5</consume_rarity>
		<ascension_level_0>
			<弓阶银棋>5</弓阶银棋>
		</ascension_level_0>
		<ascension_level_1>
			<弓阶银棋>12</弓阶银棋>
			<虚影之尘>15</虚影之尘>
		</ascension_level_1>
		<ascension_level_2>
			<弓阶金像>5</弓阶金像>
			<禁断书页>10</禁断书页>
			<无间齿轮>5</无间齿轮>
		</ascension_level_2>
		<ascension_level_3>
			<弓阶金像>12</弓阶金像>
			<无间齿轮>10</无间齿轮>
			<鬼魂提灯>12</鬼魂提灯>
		</ascension_level_3>
		<total_consume>
			<弓阶银棋>17</弓阶银棋>
			<弓阶金像>17</弓阶金像>
			<虚影之尘>15</虚影之尘>
			<鬼魂提灯>12</鬼魂提灯>
			<无间齿轮>15</无间齿轮>
			<禁断书页>10</禁断书页>
		</total_consume>
	</ascension_consume>
	<skill_1>
		<upgradable>False</upgradable>
		<icon>黄金律</icon>
		<name_sc>流电学 A</name_sc>
		<cool_time>7→5</cool_time>
	</skill_1>
	<skill_2>
		<upgradable>True</upgradable>
		<icon>毅力</icon>
		<name_sc>天赋的睿智 A</name_sc>
		<cool_time>7→5</cool_time>
	</skill_2>
	<skill_3>
		<upgradable>False</upgradable>
		<icon>充能</icon>
		<name_sc>星之开拓者 EX</name_sc>
		<cool_time>8→6</cool_time>
	</skill_3>
	<skill_consume>
		<consume_rarity>5</consume_rarity>
		<skill_level_1>
			<弓之辉石>5</弓之辉石>
		</skill_level_1>
		<skill_level_2>
			<弓之辉石>12</弓之辉石>
		</skill_level_2>
		<skill_level_3>
			<弓之魔石>5</弓之魔石>
		</skill_level_3>
		<skill_level_4>
			<弓之魔石>12</弓之魔石>
			<禁断书页>5</禁断书页>
		</skill_level_4>
		<skill_level_5>
			<弓之秘石>5</弓之秘石>
			<禁断书页>10</禁断书页>
		</skill_level_5>
		<skill_level_6>
			<弓之秘石>12</弓之秘石>
			<虚影之尘>10</虚影之尘>
		</skill_level_6>
		<skill_level_7>
			<虚影之尘>20</虚影之尘>
			<凤凰羽毛>5</凤凰羽毛>
		</skill_level_7>
		<skill_level_8>
			<凤凰羽毛>15</凤凰羽毛>
			<鬼魂提灯>24</鬼魂提灯>
		</skill_level_8>
		<skill_level_9>
			<传承结晶>1</传承结晶>
		</skill_level_9>
		<total_consume>
			<弓之辉石>17</弓之辉石>
			<弓之魔石>17</弓之魔石>
			<弓之秘石>17</弓之秘石>
			<虚影之尘>30</虚影之尘>
			<鬼魂提灯>24</鬼魂提灯>
			<凤凰羽毛>20</凤凰羽毛>
			<禁断书页>15</禁断书页>
			<传承结晶>1</传承结晶>
		</total_consume>
	</skill_consume>
</root>
