<?xml version="1.0" encoding="utf-8"?>
<root>
	<basic>
		<rarity>3</rarity>
		<id>117</id>
		<name_sc>风魔小太郎</name_sc>
		<name_jp>風魔小太郎</name_jp>
		<name_en>Fuuma 'Evil-wind' Kotarou</name_en>
		<class>Assassin</class>
		<alignments>混沌</alignments>
		<alignments>恶</alignments>
		<gender>男性</gender>
		<attribute>人</attribute>
		<atk_base>1316</atk_base>
		<hp_base>1592</hp_base>
		<atk_4>7091</atk_4>
		<hp_4>8844</hp_4>
		<atk_90>8759</atk_90>
		<hp_90>10939</hp_90>
		<atk_100>9597</atk_100>
		<hp_100>11991</hp_100>
		<atk_max>11597</atk_max>
		<hp_max>13991</hp_max>
		<card>QQQAB</card>
		<characteristic>人型</characteristic>
		<characteristic>被EA特攻</characteristic>
	</basic>
	<nobel>
		<revealable>False</revealable>
		<upgradable>True</upgradable>
		<card>Q</card>
		<level>B+</level>
		<name_sc>不灭的混沌旅团</name_sc>
		<name_jp>不滅の混沌旅団</name_jp>
		<name_en>Immortal Chaos Brigade</name_en>
	</nobel>
	<ascension_consume>
		<consume_rarity>3</consume_rarity>
		<ascension_level_0>
			<杀阶银棋>4</杀阶银棋>
		</ascension_level_0>
		<ascension_level_1>
			<杀阶银棋>8</杀阶银棋>
			<凶骨>15</凶骨>
		</ascension_level_1>
		<ascension_level_2>
			<杀阶金像>4</杀阶金像>
			<虚影之尘>13</虚影之尘>
			<八连双晶>4</八连双晶>
		</ascension_level_2>
		<ascension_level_3>
			<杀阶金像>8</杀阶金像>
			<八连双晶>7</八连双晶>
			<黑兽脂>5</黑兽脂>
		</ascension_level_3>
		<total_consume>
			<杀阶银棋>12</杀阶银棋>
			<杀阶金像>12</杀阶金像>
			<凶骨>15</凶骨>
			<虚影之尘>13</虚影之尘>
			<八连双晶>11</八连双晶>
			<黑兽脂>5</黑兽脂>
		</total_consume>
	</ascension_consume>
	<skill_1>
		<upgradable>False</upgradable>
		<icon>降攻</icon>
		<name_sc>破坏工作 B+</name_sc>
		<cool_time>7→5</cool_time>
	</skill_1>
	<skill_2>
		<upgradable>False</upgradable>
		<icon>回避</icon>
		<name_sc>忍术 A+++</name_sc>
		<cool_time>8→6</cool_time>
	</skill_2>
	<skill_3>
		<upgradable>False</upgradable>
		<icon>弱体耐性下降</icon>
		<name_sc>风声鹤唳 B</name_sc>
		<cool_time>7→5</cool_time>
	</skill_3>
	<skill_consume>
		<consume_rarity>3</consume_rarity>
		<skill_level_1>
			<杀之辉石>4</杀之辉石>
		</skill_level_1>
		<skill_level_2>
			<杀之辉石>8</杀之辉石>
		</skill_level_2>
		<skill_level_3>
			<杀之魔石>4</杀之魔石>
		</skill_level_3>
		<skill_level_4>
			<杀之魔石>8</杀之魔石>
			<虚影之尘>7</虚影之尘>
		</skill_level_4>
		<skill_level_5>
			<杀之秘石>4</杀之秘石>
			<虚影之尘>13</虚影之尘>
		</skill_level_5>
		<skill_level_6>
			<杀之秘石>8</杀之秘石>
			<凶骨>10</凶骨>
		</skill_level_6>
		<skill_level_7>
			<凶骨>20</凶骨>
			<世界树之种>5</世界树之种>
		</skill_level_7>
		<skill_level_8>
			<世界树之种>15</世界树之种>
			<混沌之爪>10</混沌之爪>
		</skill_level_8>
		<skill_level_9>
			<传承结晶>1</传承结晶>
		</skill_level_9>
		<total_consume>
			<杀之辉石>12</杀之辉石>
			<杀之魔石>12</杀之魔石>
			<杀之秘石>12</杀之秘石>
			<凶骨>30</凶骨>
			<虚影之尘>20</虚影之尘>
			<世界树之种>20</世界树之种>
			<混沌之爪>10</混沌之爪>
			<传承结晶>1</传承结晶>
		</total_consume>
	</skill_consume>
</root>
