<?xml version="1.0" encoding="utf-8"?>
<root>
	<basic>
		<rarity>5</rarity>
		<id>139</id>
		<name_sc>克娄巴特拉</name_sc>
		<name_jp>クレオパトラ</name_jp>
		<name_en>Cleopatra</name_en>
		<class>Assassin</class>
		<alignments>秩序</alignments>
		<alignments>中庸</alignments>
		<gender>女性</gender>
		<attribute>人</attribute>
		<atk_base>1713</atk_base>
		<hp_base>1965</hp_base>
		<atk_4>11088</atk_4>
		<hp_4>13402</hp_4>
		<atk_90>11088</atk_90>
		<hp_90>13402</hp_90>
		<atk_100>12138</atk_100>
		<hp_100>14682</hp_100>
		<atk_max>14138</atk_max>
		<hp_max>16682</hp_max>
		<card>QQABB</card>
		<characteristic>人型</characteristic>
		<characteristic>神性</characteristic>
		<characteristic>被EA特攻</characteristic>
		<characteristic>王</characteristic>
		<nickname>艳后</nickname>
	</basic>
	<nobel>
		<revealable>False</revealable>
		<upgradable>False</upgradable>
		<card>B</card>
		<level>A</level>
		<name_sc>终结破晓之蛇啊，降临此处</name_sc>
		<name_jp>暁の時を終える蛇よ、此処に</name_jp>
		<name_en>Uraeus Astrape</name_en>
	</nobel>
	<ascension_consume>
		<consume_rarity>5</consume_rarity>
		<ascension_level_0>
			<杀阶银棋>5</杀阶银棋>
		</ascension_level_0>
		<ascension_level_1>
			<杀阶银棋>12</杀阶银棋>
			<凤凰羽毛>6</凤凰羽毛>
		</ascension_level_1>
		<ascension_level_2>
			<杀阶金像>5</杀阶金像>
			<封魔之灯>6</封魔之灯>
			<血之泪石>3</血之泪石>
		</ascension_level_2>
		<ascension_level_3>
			<杀阶金像>12</杀阶金像>
			<血之泪石>6</血之泪石>
			<蛇之宝玉>10</蛇之宝玉>
		</ascension_level_3>
		<total_consume>
			<杀阶银棋>17</杀阶银棋>
			<杀阶金像>17</杀阶金像>
			<蛇之宝玉>10</蛇之宝玉>
			<凤凰羽毛>6</凤凰羽毛>
			<血之泪石>9</血之泪石>
			<封魔之灯>6</封魔之灯>
		</total_consume>
	</ascension_consume>
	<skill_1>
		<upgradable>False</upgradable>
		<icon>回血</icon>
		<name_sc>皇帝特权 A</name_sc>
		<cool_time>7→5</cool_time>
	</skill_1>
	<skill_2>
		<upgradable>False</upgradable>
		<icon>回合充能</icon>
		<name_sc>黄金律（富&amp;体） B</name_sc>
		<cool_time>8→6</cool_time>
	</skill_2>
	<skill_3>
		<upgradable>False</upgradable>
		<icon>无敌</icon>
		<name_sc>女神的加护 C</name_sc>
		<cool_time>8→6</cool_time>
	</skill_3>
	<skill_consume>
		<consume_rarity>5</consume_rarity>
		<skill_level_1>
			<杀之辉石>5</杀之辉石>
		</skill_level_1>
		<skill_level_2>
			<杀之辉石>12</杀之辉石>
		</skill_level_2>
		<skill_level_3>
			<杀之魔石>5</杀之魔石>
		</skill_level_3>
		<skill_level_4>
			<杀之魔石>12</杀之魔石>
			<封魔之灯>3</封魔之灯>
		</skill_level_4>
		<skill_level_5>
			<杀之秘石>5</杀之秘石>
			<封魔之灯>6</封魔之灯>
		</skill_level_5>
		<skill_level_6>
			<杀之秘石>12</杀之秘石>
			<凤凰羽毛>4</凤凰羽毛>
		</skill_level_6>
		<skill_level_7>
			<凤凰羽毛>8</凤凰羽毛>
			<追忆的贝壳>6</追忆的贝壳>
		</skill_level_7>
		<skill_level_8>
			<追忆的贝壳>18</追忆的贝壳>
			<智慧之圣甲虫像>10</智慧之圣甲虫像>
		</skill_level_8>
		<skill_level_9>
			<传承结晶>1</传承结晶>
		</skill_level_9>
		<total_consume>
			<杀之辉石>17</杀之辉石>
			<杀之魔石>17</杀之魔石>
			<杀之秘石>17</杀之秘石>
			<凤凰羽毛>12</凤凰羽毛>
			<追忆的贝壳>24</追忆的贝壳>
			<封魔之灯>9</封魔之灯>
			<智慧之圣甲虫像>10</智慧之圣甲虫像>
			<传承结晶>1</传承结晶>
		</total_consume>
	</skill_consume>
</root>
