<?xml version="1.0" encoding="utf-8"?>
<root>
	<basic>
		<rarity>4</rarity>
		<id>185</id>
		<name_sc>望月千代女</name_sc>
		<name_jp>望月千代女</name_jp>
		<name_en>Mochizuki Chiyome</name_en>
		<class>Assassin</class>
		<alignments>混沌</alignments>
		<alignments>恶</alignments>
		<gender>女性</gender>
		<attribute>地</attribute>
		<atk_base>1418</atk_base>
		<hp_base>1862</hp_base>
		<atk_4>8510</atk_4>
		<hp_4>11637</hp_4>
		<atk_90>9403</atk_90>
		<hp_90>12868</hp_90>
		<atk_100>10304</atk_100>
		<hp_100>14110</hp_100>
		<atk_max>12304</atk_max>
		<hp_max>16110</hp_max>
		<card>QQAAB</card>
		<characteristic>人型</characteristic>
		<characteristic>被EA特攻</characteristic>
		<characteristic>天地从者</characteristic>
	</basic>
	<nobel>
		<revealable>True</revealable>
		<upgradable>False</upgradable>
		<card>A</card>
		<level>C</level>
		<name_sc>通灵·伊吹大明神缘起</name_sc>
		<name_jp>口寄せ·伊吹大明神縁起</name_jp>
		<name_en>Kuchiyose·Ibuki Daimyōjin Engi</name_en>
	</nobel>
	<ascension_consume>
		<consume_rarity>4</consume_rarity>
		<ascension_level_0>
			<杀阶银棋>4</杀阶银棋>
		</ascension_level_0>
		<ascension_level_1>
			<杀阶银棋>10</杀阶银棋>
			<万死的毒针>15</万死的毒针>
		</ascension_level_1>
		<ascension_level_2>
			<杀阶金像>4</杀阶金像>
			<枯淡勾玉>8</枯淡勾玉>
			<精灵根>2</精灵根>
		</ascension_level_2>
		<ascension_level_3>
			<杀阶金像>10</杀阶金像>
			<精灵根>4</精灵根>
			<咒兽胆石>4</咒兽胆石>
		</ascension_level_3>
		<total_consume>
			<杀阶银棋>14</杀阶银棋>
			<杀阶金像>14</杀阶金像>
			<万死的毒针>15</万死的毒针>
			<枯淡勾玉>8</枯淡勾玉>
			<精灵根>6</精灵根>
			<咒兽胆石>4</咒兽胆石>
		</total_consume>
	</ascension_consume>
	<skill_1>
		<upgradable>False</upgradable>
		<icon>封印</icon>
		<name_sc>咒术（巫） C</name_sc>
		<cool_time>7→5</cool_time>
	</skill_1>
	<skill_2>
		<upgradable>False</upgradable>
		<icon>蓝放</icon>
		<name_sc>大蛇诅咒 B</name_sc>
		<cool_time>7→5</cool_time>
	</skill_2>
	<skill_3>
		<upgradable>False</upgradable>
		<icon>回避</icon>
		<name_sc>甲贺流 A</name_sc>
		<cool_time>8→6</cool_time>
	</skill_3>
	<skill_consume>
		<consume_rarity>4</consume_rarity>
		<skill_level_1>
			<杀之辉石>4</杀之辉石>
		</skill_level_1>
		<skill_level_2>
			<杀之辉石>10</杀之辉石>
		</skill_level_2>
		<skill_level_3>
			<杀之魔石>4</杀之魔石>
		</skill_level_3>
		<skill_level_4>
			<杀之魔石>10</杀之魔石>
			<枯淡勾玉>4</枯淡勾玉>
		</skill_level_4>
		<skill_level_5>
			<杀之秘石>4</杀之秘石>
			<枯淡勾玉>8</枯淡勾玉>
		</skill_level_5>
		<skill_level_6>
			<杀之秘石>10</杀之秘石>
			<万死的毒针>10</万死的毒针>
		</skill_level_6>
		<skill_level_7>
			<万死的毒针>20</万死的毒针>
			<混沌之爪>3</混沌之爪>
		</skill_level_7>
		<skill_level_8>
			<混沌之爪>9</混沌之爪>
			<虚影之尘>40</虚影之尘>
		</skill_level_8>
		<skill_level_9>
			<传承结晶>1</传承结晶>
		</skill_level_9>
		<total_consume>
			<杀之辉石>14</杀之辉石>
			<杀之魔石>14</杀之魔石>
			<杀之秘石>14</杀之秘石>
			<虚影之尘>40</虚影之尘>
			<万死的毒针>30</万死的毒针>
			<枯淡勾玉>12</枯淡勾玉>
			<混沌之爪>12</混沌之爪>
			<传承结晶>1</传承结晶>
		</total_consume>
	</skill_consume>
</root>
